ai_api_wrapper/__init__.py
ai_api_wrapper/client.py
ai_api_wrapper/config/config_schema.py
ai_api_wrapper/config/default_config.py
ai_api_wrapper/examples/config_examples/.env.example
ai_api_wrapper/examples/config_examples/advanced_config.yaml
ai_api_wrapper/framework/__init__.py
ai_api_wrapper/framework/chat_completion_response.py
ai_api_wrapper/framework/choice.py
ai_api_wrapper/framework/message.py
ai_api_wrapper/framework/provider_interface.py
ai_api_wrapper/provider.py
ai_api_wrapper/providers/__init__.py
ai_api_wrapper/providers/anthropic_provider.py
ai_api_wrapper/providers/aws_provider.py
ai_api_wrapper/providers/azure_provider.py
ai_api_wrapper/providers/deepseek_provider.py
ai_api_wrapper/providers/fireworks_provider.py
ai_api_wrapper/providers/google_provider.py
ai_api_wrapper/providers/grok_provider.py
ai_api_wrapper/providers/groq_provider.py
ai_api_wrapper/providers/huggingface_provider.py
ai_api_wrapper/providers/message_converter.py
ai_api_wrapper/providers/mistral_provider.py
ai_api_wrapper/providers/ollama_provider.py
ai_api_wrapper/providers/openai_provider.py
ai_api_wrapper/providers/openrouter_provider.py
ai_api_wrapper/utils/config_manager.py
ai_api_wrapper/utils/constants.py
ai_api_wrapper/utils/logger.py
ai_api_wrapper/utils/tools.py
ai_api_wrapper/utils/utils.py
ai_api_wrapper-0.1.3.dist-info/LICENSE
ai_api_wrapper-0.1.3.dist-info/METADATA
ai_api_wrapper-0.1.3.dist-info/WHEEL
ai_api_wrapper-0.1.3.dist-info/RECORD
